odoo/addons/edi_voxel_stock_picking_oca/README.rst
odoo/addons/edi_voxel_stock_picking_oca/__init__.py
odoo/addons/edi_voxel_stock_picking_oca/__manifest__.py
odoo/addons/edi_voxel_stock_picking_oca/data/ir_cron_data.xml
odoo/addons/edi_voxel_stock_picking_oca/i18n/edi_voxel_stock_picking_oca.pot
odoo/addons/edi_voxel_stock_picking_oca/i18n/es.po
odoo/addons/edi_voxel_stock_picking_oca/i18n/it.po
odoo/addons/edi_voxel_stock_picking_oca/models/__init__.py
odoo/addons/edi_voxel_stock_picking_oca/models/res_company.py
odoo/addons/edi_voxel_stock_picking_oca/models/res_config_settings.py
odoo/addons/edi_voxel_stock_picking_oca/models/res_partner.py
odoo/addons/edi_voxel_stock_picking_oca/models/stock_picking.py
odoo/addons/edi_voxel_stock_picking_oca/readme/CONFIGURE.md
odoo/addons/edi_voxel_stock_picking_oca/readme/CONTRIBUTORS.md
odoo/addons/edi_voxel_stock_picking_oca/readme/DESCRIPTION.md
odoo/addons/edi_voxel_stock_picking_oca/readme/USAGE.md
odoo/addons/edi_voxel_stock_picking_oca/reports/__init__.py
odoo/addons/edi_voxel_stock_picking_oca/reports/report_voxel_picking.py
odoo/addons/edi_voxel_stock_picking_oca/static/description/icon.png
odoo/addons/edi_voxel_stock_picking_oca/static/description/index.html
odoo/addons/edi_voxel_stock_picking_oca/tests/__init__.py
odoo/addons/edi_voxel_stock_picking_oca/tests/test_voxel_stock_picking.py
odoo/addons/edi_voxel_stock_picking_oca/views/report_voxel_picking.xml
odoo/addons/edi_voxel_stock_picking_oca/views/res_company_view.xml
odoo/addons/edi_voxel_stock_picking_oca/views/res_config_settings_views.xml
odoo/addons/edi_voxel_stock_picking_oca/views/res_partner_view.xml
odoo/addons/edi_voxel_stock_picking_oca/views/stock_picking_views.xml
odoo_addon_edi_voxel_stock_picking_oca-18.0.1.0.0.4.dist-info/METADATA
odoo_addon_edi_voxel_stock_picking_oca-18.0.1.0.0.4.dist-info/WHEEL
odoo_addon_edi_voxel_stock_picking_oca-18.0.1.0.0.4.dist-info/top_level.txt
odoo_addon_edi_voxel_stock_picking_oca-18.0.1.0.0.4.dist-info/RECORD
