Metadata-Version: 2.1
Name: odoo-addon-edi_voxel_stock_picking_oca
Version: 18.0.1.0.0.4
Requires-Python: >=3.10
Requires-Dist: odoo-addon-edi_voxel_oca==18.0.*
Requires-Dist: odoo==18.0.*
Summary: Sends stock picking report to Voxel.
Home-page: https://github.com/OCA/edi
License: AGPL-3
Author: Tecnativa, Odoo Community Association (OCA)
Author-email: support@odoo-community.org
Classifier: Programming Language :: Python
Classifier: Framework :: Odoo
Classifier: Framework :: Odoo :: 18.0
Classifier: License :: OSI Approved :: GNU Affero General Public License v3
